pixelart/__init__.py
pixelart/cli.py
pixelart/gui.py
pixelart/processing.py
pixelart/textures.py
pixelart-0.1.1.dist-info/DESCRIPTION.rst
pixelart-0.1.1.dist-info/METADATA
pixelart-0.1.1.dist-info/RECORD
pixelart-0.1.1.dist-info/WHEEL
pixelart-0.1.1.dist-info/entry_points.txt
pixelart-0.1.1.dist-info/metadata.json
pixelart-0.1.1.dist-info/top_level.txt
