Metadata-Version: 2.0
Name: pixelart
Version: 0.1.1
Summary: Match images to minecraft textures
Home-page: https://github.com/lekro/pixelart
Author: lekro
Author-email: kapuraya@gmail.com
License: MIT
Keywords: pixel,art,pixelart,minecraft
Platform: UNKNOWN
Classifier: Development Status :: 3 - Alpha
Classifier: Intended Audience :: End Users/Desktop
Classifier: Topic :: Games/Entertainment
Classifier: License :: OSI Approved :: MIT License
Classifier: Programming Language :: Python :: 3
Requires-Python: >=3.2
Requires-Dist: Pillow
Requires-Dist: numpy
Provides-Extra: faster nearest neighbors matching
Requires-Dist: scipy; extra == 'faster nearest neighbors matching'
